README.txt
setup.cfg
setup.py
Products/__init__.py
Products.basesyndication.egg-info/PKG-INFO
Products.basesyndication.egg-info/SOURCES.txt
Products.basesyndication.egg-info/dependency_links.txt
Products.basesyndication.egg-info/entry_points.txt
Products.basesyndication.egg-info/namespace_packages.txt
Products.basesyndication.egg-info/not-zip-safe
Products.basesyndication.egg-info/requires.txt
Products.basesyndication.egg-info/top_level.txt
Products/basesyndication/DEPENDENCIES.txt
Products/basesyndication/IGNORE.txt
Products/basesyndication/TODO.txt
Products/basesyndication/__init__.py
Products/basesyndication/interfaces.py
Products/basesyndication/version.txt
Products/basesyndication/browser/__init__.py
Products/basesyndication/browser/atom.xml.pt
Products/basesyndication/browser/feed.rdf.pt
Products/basesyndication/browser/feed11.rdf.pt
Products/basesyndication/browser/itunes.xml.pt
Products/basesyndication/browser/rss.xml.pt
docs/HISTORY.txt
docs/INSTALL.txt
docs/LICENSE.GPL
docs/LICENSE.txt