Metadata-Version: 1.0
Name: Products.basesyndication
Version: 1.0.0
Summary: Basic Syndication interfaces and templates
Home-page: http://dev.plone.org/collective/browser/Products.basesyndication
Author: Tim Hicks
Author-email: tim@sitefusion.co.uk
License: GPL
Keywords: plone syndication atom rss
Platform: UNKNOWN
Classifier: Framework :: Plone
Classifier: Framework :: Zope2
Classifier: Framework :: Zope3
Classifier: Programming Language :: Python
Classifier: Topic :: Software Development :: Libraries :: Python Modules
